{ "13501801181":  {"client": "http://yiw1.dc.houdeyun.cn:64336/"},
  "13501801180": {"client": "http://yiw1.dc.houdeyun.cn:64336/"},
  "13429410782": {"client": "http://yiw1.dc.houdeyun.cn:64336/"},
  "15206258723": {"client": "http://zhy1.dc.houdeyun.cn:50832/"},
  "18606520623": {"client": "http://zhy1.dc.houdeyun.cn:61099/"},
  "18668361776": {"client": "http://zhy1.dc.houdeyun.cn:52301/"},
  "13456244559": {"client": "http://zhy1.dc.houdeyun.cn:59263/"},
  "18120768460": {"client": "http://zhy1.dc.houdeyun.cn:56006/"},
  "13774209448": {"client": "http://zhy1.dc.houdeyun.cn:52947/"},
  "17278973461": {"client": "http://zhy1.dc.houdeyun.cn:64303/"},
  "15824396172": {"client": "http://101.43.29.249:7865/"},
  "15067598035": {"client": "http://zhy1.dc.houdeyun.cn:55412/"},
  "15968392234": {"client": "http://zhy1.dc.houdeyun.cn:60558/"},
  "13866668888": {"client": "http://zhy1.dc.houdeyun.cn:50354/"},
"15870915793": {"client": "http://zhy1.dc.houdeyun.cn:59715/"},
"13456244559": {"client": "http://zhy1.dc.houdeyun.cn:61390/"}}